seta/__init__.py
seta/core.py
seta_datasets-1.0.2.dist-info/licenses/LICENSE
seta_datasets-1.0.2.dist-info/METADATA
seta_datasets-1.0.2.dist-info/WHEEL
seta_datasets-1.0.2.dist-info/top_level.txt
seta_datasets-1.0.2.dist-info/RECORD
