Metadata-Version: 2.4
Name: seta-datasets
Version: 1.0.2
Summary: Official dataset loader for SETA Protocol with authentication support.
Author-email: Himanshu <himanshu.madhunala1@gmail.com>
Keywords: data,seta,loader,datasets,machine-learning
Classifier: Programming Language :: Python :: 3
Classifier: Operating System :: OS Independent
Requires-Python: >=3.7
License-File: LICENSE
Requires-Dist: requests>=2.28.0
Requires-Dist: rich>=12.0.0
Dynamic: license-file
